[{"id_clients":null,"nom":"Rogers","prenom":"Steve","adresse":"75012","codep":null,"ville":"PARIS","tel":null,"mail":"steve.rogers@yahoo.com"},{"id_clients":null,"nom":"Banner","prenom":"Bruce","adresse":"33150","codep":null,"ville":"CENON","tel":null,"mail":"bruce.banner@gmail.com"},{"id_clients":null,"nom":"Barton","prenom":"Clint","adresse":"91270","codep":null,"ville":"VIGNEUX-SUR-SEINE","tel":null,"mail":"clint.barton@outlook.com"},{"id_clients":null,"nom":"Prince","prenom":"Diana","adresse":"77380","codep":null,"ville":"COMBS-LA-VILLE","tel":null,"mail":"diana.prince@hotmail.fr"},{"id_clients":null,"nom":"Gordon","prenom":"Jim","adresse":"78280","codep":null,"ville":"GUYANCOURT","tel":null,"mail":"jim.gordon@hotmail.fr"},{"id_clients":null,"nom":"Dent","prenom":"Harvey","adresse":"21000","codep":null,"ville":"DIJON","tel":null,"mail":"harvey.dent@gmail.com"}]